caramel/__init__.py
caramel/config.py
caramel/models.py
caramel/views.py
caramel/scripts/__init__.py
caramel/scripts/autosign.py
caramel/scripts/generate_ca.py
caramel/scripts/initializedb.py
caramel/scripts/tool.py
caramel/static/favicon.ico
caramel/static/footerbg.png
caramel/static/headerbg.png
caramel/static/ie6.css
caramel/static/middlebg.png
caramel/static/pylons.css
caramel/static/pyramid-small.png
caramel/static/pyramid.png
caramel/static/transparent.gif
caramel/templates/mytemplate.pt
tests/__init__.py
tests/fixtures.py
tests/test_config.py
tests/test_models.py
tests/test_views.py
caramel-1.9.6.dist-info/LICENSE
caramel-1.9.6.dist-info/METADATA
caramel-1.9.6.dist-info/WHEEL
caramel-1.9.6.dist-info/entry_points.txt
caramel-1.9.6.dist-info/top_level.txt
caramel-1.9.6.dist-info/RECORD
