Metadata-Version: 2.1
Name: caramel
Version: 1.9.6
Summary: caramel
Home-page: https://github.com/MyTemp/caramel
Author: D.S. Ljungmark
Author-email: spider@modio.se
Keywords: web wsgi bfg pylons pyramid certificates x509 ca cert ssl tls
Classifier: Programming Language :: Python
Classifier: Framework :: Pyramid
Classifier: Topic :: Internet :: WWW/HTTP
Classifier: Topic :: Internet :: WWW/HTTP :: WSGI :: Application
Requires-Python: >=3.7
License-File: LICENSE
Requires-Dist: pyramid
Requires-Dist: SQLAlchemy ~=1.4.32
Requires-Dist: transaction
Requires-Dist: pyramid-tm
Requires-Dist: zope.sqlalchemy >=1.6
Requires-Dist: waitress
Requires-Dist: cryptography >=38
Requires-Dist: pyOpenSSL >=22.0.0
Requires-Dist: python-dateutil
Requires-Dist: legacy-cgi ; python_version >= "3.13"
